Metadata-Version: 1.1
Name: simple-image-debayer
Version: 0.0.4
Summary: Python3 library for debayering images using OpenCV.
Home-page: https://github.com/waikato-datamining/simple-image-debayer
Author: Peter Reutemann
Author-email: fracpete@waikato.ac.nz
License: MIT License
Platform: UNKNOWN
Classifier: Development Status :: 4 - Beta
Classifier: License :: OSI Approved :: MIT License
Classifier: Topic :: Multimedia :: Graphics
Classifier: Programming Language :: Python :: 3
